meteorology_conversion/__init__.py
meteorology_conversion/meteorology_conversion.py
meteorology_conversion/version.py
meteorology_conversion-1.0.3.dist-info/licenses/LICENSE
meteorology_conversion-1.0.3.dist-info/METADATA
meteorology_conversion-1.0.3.dist-info/WHEEL
meteorology_conversion-1.0.3.dist-info/top_level.txt
meteorology_conversion-1.0.3.dist-info/RECORD
